[
  {
    "type": "csharp-method",
    "name": "AssignDataModel",
    "source_file": "D:\\NEVOWEB\\Project\\DesktopModules\\DNNRocketModules\\RocketEventsAPI\\Render\\RocketEventsTokens.cs",
    "description": "Assigns and prepares the data model for Razor event templates. It calls the base class\u0027s AssignDataModel, sets up date parameters for calendar views, and populates several event lists (next events, past events, monthly events, etc.) into the SimplisityRazor model.",
    "signature": "public new string AssignDataModel(SimplisityRazor sModel)",
    "classname": "RocketEventsAPITokens",
    "isstatic": "false",
    "namespace": "RocketEventsAPI.Components",
    "parameters": [
      {
        "name": "sModel",
        "type": "SimplisityRazor",
        "description": ""
      }
    ],
    "returns": "string"
  },
  {
    "type": "csharp-method",
    "name": "RssEventUrl",
    "source_file": "D:\\NEVOWEB\\Project\\DesktopModules\\DNNRocketModules\\RocketEventsAPI\\Render\\RocketEventsTokens.cs",
    "description": "Generates a URL for an RSS feed of events for a specific month and year. The URL includes parameters for the command, month, year, and a SQL index for sorting by event start date.",
    "signature": "public IEncodedString RssEventUrl(int portalId, string cmd, int monthDate, int yearDate)",
    "classname": "RocketEventsAPITokens",
    "isstatic": "false",
    "namespace": "RocketEventsAPI.Components",
    "parameters": [
      {
        "name": "portalId",
        "type": "int",
        "description": ""
      },
      {
        "name": "cmd",
        "type": "string",
        "description": ""
      },
      {
        "name": "monthDate",
        "type": "int",
        "description": ""
      },
      {
        "name": "yearDate",
        "type": "int",
        "description": ""
      }
    ],
    "returns": "IEncodedString"
  }
]